pymoth/Clock.py
pymoth/DataSet.py
pymoth/Frame.py
pymoth/Instance.py
pymoth/Namespace.py
pymoth/Sequence.py
pymoth/__init__.py
pymoth/formats.py
pymoth/utils.py
pymoth-0.0.3.dist-info/METADATA
pymoth-0.0.3.dist-info/RECORD
pymoth-0.0.3.dist-info/WHEEL
pymoth-0.0.3.dist-info/top_level.txt
