Metadata-Version: 2.1
Name: pymoth
Version: 0.0.3
Summary: A package for handling MOTChallenge data sets
Home-page: https://github.com/samuelwestlake/pymoth
Author: Samuel Westlake
Author-email: s.t.westlake@cranfield.ac.uk
License: UNKNOWN
Platform: UNKNOWN
Classifier: Programming Language :: Python :: 3
Classifier: License :: OSI Approved :: MIT License
Classifier: Operating System :: OS Independent
